avocado_runner_vm/__init__.py
avocado_framework_plugin_runner_vm-80.0.dist-info/METADATA
avocado_framework_plugin_runner_vm-80.0.dist-info/WHEEL
avocado_framework_plugin_runner_vm-80.0.dist-info/entry_points.txt
avocado_framework_plugin_runner_vm-80.0.dist-info/top_level.txt
avocado_framework_plugin_runner_vm-80.0.dist-info/RECORD
