Metadata-Version: 2.1
Name: avocado-framework-plugin-runner-vm
Version: 80.0
Summary: Avocado Runner for libvirt VM Execution
Home-page: http://avocado-framework.github.io/
Author: Avocado Developers
Author-email: avocado-devel@redhat.com
License: UNKNOWN
Platform: UNKNOWN
Requires-Dist: avocado-framework-plugin-runner-remote (==80.0)
Requires-Dist: libvirt-python
